README.md
setup.cfg
setup.py
koe_acoustic_features/__init__.py
koe_acoustic_features/extractor.py
koe_acoustic_features/freq_domain.py
koe_acoustic_features/linear_prediction.py
koe_acoustic_features/mt_features.py
koe_acoustic_features/other_features.py
koe_acoustic_features/scaled_freq_features.py
koe_acoustic_features/time_domain.py
koe_acoustic_features/utils.py
koe_acoustic_features/wavfile.py
koe_acoustic_features.egg-info/PKG-INFO
koe_acoustic_features.egg-info/SOURCES.txt
koe_acoustic_features.egg-info/dependency_links.txt
koe_acoustic_features.egg-info/requires.txt
koe_acoustic_features.egg-info/top_level.txt
tests/__init__.py
tests/test_all.py