Metadata-Version: 2.1
Name: koe-acoustic-features
Version: 0.0.2
Summary: Implementation of acoustic features used by Koe
Home-page: https://github.com/fzyukio/koe-acoustic-features
Author: Yukio Fukuzawa
Author-email: y.fukuzawa@massey.ac.nz
License: UNKNOWN
Platform: UNKNOWN
Classifier: Programming Language :: Python :: 3
Classifier: License :: OSI Approved :: MIT License
Classifier: Operating System :: OS Independent
